shapeforge/__init__.py
shapeforge-0.1.0.dist-info/licenses/LICENSE
shapeforge-0.1.0.dist-info/METADATA
shapeforge-0.1.0.dist-info/WHEEL
shapeforge-0.1.0.dist-info/top_level.txt
shapeforge-0.1.0.dist-info/RECORD
