Metadata-Version: 2.4
Name: shapeforge
Version: 0.1.0
Summary: A Python package for generating 2D or 3D domain containing geometry shapes of interest, following a specified distribution.
Author-email: Rajesh Nakka <338rajesh@gmail.com>
Maintainer-email: Rajesh Nakka <338rajesh@gmail.com>
License: MIT License
Project-URL: Homepage, https://github.com/338rajesh/shapeforge
Project-URL: Repository, https://github.com/338rajesh/shapeforge
Project-URL: Issues, https://github.com/338rajesh/shapeforge/issues
Keywords: Geometry,RVE,Equivalent Volume Element,UnitCell
Classifier: Development Status :: 1 - Planning
Classifier: Intended Audience :: Science/Research
Classifier: Topic :: Scientific/Engineering :: Physics
Classifier: Programming Language :: Python :: 3
Classifier: License :: OSI Approved :: MIT License
Classifier: Operating System :: OS Independent
Requires-Python: >=3.11
License-File: LICENSE
Requires-Dist: gbox>=0.2.0
Requires-Dist: numpy>=2.2.0
Requires-Dist: scipy>=1.15.2
Requires-Dist: matplotlib>=3.10.0
Provides-Extra: dev
Requires-Dist: pytest>=8.4.0; extra == "dev"
Dynamic: license-file
